<?xml version="1.0" encoding="UTF-8" standalone="yes"?>
<pc:chgInfo xmlns:a="http://schemas.openxmlformats.org/drawingml/2006/main" xmlns:r="http://schemas.openxmlformats.org/officeDocument/2006/relationships" xmlns:ac="http://schemas.microsoft.com/office/drawing/2013/main/command" xmlns:pc="http://schemas.microsoft.com/office/powerpoint/2013/main/command"><pc:docChgLst><pc:chgData name="Alicia Esparza" userId="65b59e52a21d66fc" providerId="LiveId" clId="{01525AF4-9CFC-4414-9EAF-33FDE438DE6A}"/><pc:docChg chg="undo custSel addSld delSld modSld sldOrd"><pc:chgData name="Alicia Esparza" userId="65b59e52a21d66fc" providerId="LiveId" clId="{01525AF4-9CFC-4414-9EAF-33FDE438DE6A}" dt="2026-04-13T02:52:07.251" v="1129" actId="478"/><pc:docMkLst><pc:docMk/></pc:docMkLst><pc:sldChg chg="modSp mod"><pc:chgData name="Alicia Esparza" userId="65b59e52a21d66fc" providerId="LiveId" clId="{01525AF4-9CFC-4414-9EAF-33FDE438DE6A}" dt="2026-04-12T23:59:25.642" v="944" actId="20577"/><pc:sldMkLst><pc:docMk/><pc:sldMk cId="0" sldId="256"/></pc:sldMkLst><pc:spChg chg="mod"><ac:chgData name="Alicia Esparza" userId="65b59e52a21d66fc" providerId="LiveId" clId="{01525AF4-9CFC-4414-9EAF-33FDE438DE6A}" dt="2026-04-12T23:59:04.952" v="934" actId="20577"/><ac:spMkLst><pc:docMk/><pc:sldMk cId="0" sldId="256"/><ac:spMk id="7" creationId="{00000000-0000-0000-0000-000000000000}"/></ac:spMkLst></pc:spChg><pc:spChg chg="mod"><ac:chgData name="Alicia Esparza" userId="65b59e52a21d66fc" providerId="LiveId" clId="{01525AF4-9CFC-4414-9EAF-33FDE438DE6A}" dt="2026-04-12T23:59:25.642" v="944" actId="20577"/><ac:spMkLst><pc:docMk/><pc:sldMk cId="0" sldId="256"/><ac:spMk id="8" creationId="{00000000-0000-0000-0000-000000000000}"/></ac:spMkLst></pc:spChg></pc:sldChg><pc:sldChg chg="delSp modSp mod"><pc:chgData name="Alicia Esparza" userId="65b59e52a21d66fc" providerId="LiveId" clId="{01525AF4-9CFC-4414-9EAF-33FDE438DE6A}" dt="2026-04-12T21:33:02.478" v="538" actId="20577"/><pc:sldMkLst><pc:docMk/><pc:sldMk cId="0" sldId="257"/></pc:sldMkLst><pc:spChg chg="mod"><ac:chgData name="Alicia Esparza" userId="65b59e52a21d66fc" providerId="LiveId" clId="{01525AF4-9CFC-4414-9EAF-33FDE438DE6A}" dt="2026-04-12T21:22:58.583" v="465" actId="20577"/><ac:spMkLst><pc:docMk/><pc:sldMk cId="0" sldId="257"/><ac:spMk id="4" creationId="{00000000-0000-0000-0000-000000000000}"/></ac:spMkLst></pc:spChg><pc:spChg chg="mod"><ac:chgData name="Alicia Esparza" userId="65b59e52a21d66fc" providerId="LiveId" clId="{01525AF4-9CFC-4414-9EAF-33FDE438DE6A}" dt="2026-04-12T21:24:49.034" v="477" actId="20577"/><ac:spMkLst><pc:docMk/><pc:sldMk cId="0" sldId="257"/><ac:spMk id="7" creationId="{00000000-0000-0000-0000-000000000000}"/></ac:spMkLst></pc:spChg><pc:spChg chg="mod"><ac:chgData name="Alicia Esparza" userId="65b59e52a21d66fc" providerId="LiveId" clId="{01525AF4-9CFC-4414-9EAF-33FDE438DE6A}" dt="2026-04-12T21:24:58.902" v="481" actId="20577"/><ac:spMkLst><pc:docMk/><pc:sldMk cId="0" sldId="257"/><ac:spMk id="10" creationId="{00000000-0000-0000-0000-000000000000}"/></ac:spMkLst></pc:spChg><pc:spChg chg="mod"><ac:chgData name="Alicia Esparza" userId="65b59e52a21d66fc" providerId="LiveId" clId="{01525AF4-9CFC-4414-9EAF-33FDE438DE6A}" dt="2026-04-12T21:25:53.213" v="495" actId="20577"/><ac:spMkLst><pc:docMk/><pc:sldMk cId="0" sldId="257"/><ac:spMk id="13" creationId="{00000000-0000-0000-0000-000000000000}"/></ac:spMkLst></pc:spChg><pc:spChg chg="mod"><ac:chgData name="Alicia Esparza" userId="65b59e52a21d66fc" providerId="LiveId" clId="{01525AF4-9CFC-4414-9EAF-33FDE438DE6A}" dt="2026-04-12T21:26:23.250" v="501" actId="20577"/><ac:spMkLst><pc:docMk/><pc:sldMk cId="0" sldId="257"/><ac:spMk id="14" creationId="{00000000-0000-0000-0000-000000000000}"/></ac:spMkLst></pc:spChg><pc:spChg chg="mod"><ac:chgData name="Alicia Esparza" userId="65b59e52a21d66fc" providerId="LiveId" clId="{01525AF4-9CFC-4414-9EAF-33FDE438DE6A}" dt="2026-04-12T21:25:25.014" v="491" actId="20577"/><ac:spMkLst><pc:docMk/><pc:sldMk cId="0" sldId="257"/><ac:spMk id="16" creationId="{00000000-0000-0000-0000-000000000000}"/></ac:spMkLst></pc:spChg><pc:spChg chg="mod"><ac:chgData name="Alicia Esparza" userId="65b59e52a21d66fc" providerId="LiveId" clId="{01525AF4-9CFC-4414-9EAF-33FDE438DE6A}" dt="2026-04-12T21:27:06.749" v="505" actId="20577"/><ac:spMkLst><pc:docMk/><pc:sldMk cId="0" sldId="257"/><ac:spMk id="19" creationId="{00000000-0000-0000-0000-000000000000}"/></ac:spMkLst></pc:spChg><pc:spChg chg="mod"><ac:chgData name="Alicia Esparza" userId="65b59e52a21d66fc" providerId="LiveId" clId="{01525AF4-9CFC-4414-9EAF-33FDE438DE6A}" dt="2026-04-12T21:28:06.395" v="517" actId="20577"/><ac:spMkLst><pc:docMk/><pc:sldMk cId="0" sldId="257"/><ac:spMk id="25" creationId="{00000000-0000-0000-0000-000000000000}"/></ac:spMkLst></pc:spChg><pc:spChg chg="mod"><ac:chgData name="Alicia Esparza" userId="65b59e52a21d66fc" providerId="LiveId" clId="{01525AF4-9CFC-4414-9EAF-33FDE438DE6A}" dt="2026-04-12T21:28:25.086" v="523" actId="20577"/><ac:spMkLst><pc:docMk/><pc:sldMk cId="0" sldId="257"/><ac:spMk id="27" creationId="{00000000-0000-0000-0000-000000000000}"/></ac:spMkLst></pc:spChg><pc:spChg chg="del"><ac:chgData name="Alicia Esparza" userId="65b59e52a21d66fc" providerId="LiveId" clId="{01525AF4-9CFC-4414-9EAF-33FDE438DE6A}" dt="2026-04-12T21:32:08.264" v="524" actId="478"/><ac:spMkLst><pc:docMk/><pc:sldMk cId="0" sldId="257"/><ac:spMk id="28" creationId="{00000000-0000-0000-0000-000000000000}"/></ac:spMkLst></pc:spChg><pc:spChg chg="mod"><ac:chgData name="Alicia Esparza" userId="65b59e52a21d66fc" providerId="LiveId" clId="{01525AF4-9CFC-4414-9EAF-33FDE438DE6A}" dt="2026-04-12T21:32:42.227" v="532" actId="20577"/><ac:spMkLst><pc:docMk/><pc:sldMk cId="0" sldId="257"/><ac:spMk id="30" creationId="{00000000-0000-0000-0000-000000000000}"/></ac:spMkLst></pc:spChg><pc:spChg chg="mod"><ac:chgData name="Alicia Esparza" userId="65b59e52a21d66fc" providerId="LiveId" clId="{01525AF4-9CFC-4414-9EAF-33FDE438DE6A}" dt="2026-04-12T21:33:02.478" v="538" actId="20577"/><ac:spMkLst><pc:docMk/><pc:sldMk cId="0" sldId="257"/><ac:spMk id="33" creationId="{00000000-0000-0000-0000-000000000000}"/></ac:spMkLst></pc:spChg></pc:sldChg><pc:sldChg chg="modSp mod"><pc:chgData name="Alicia Esparza" userId="65b59e52a21d66fc" providerId="LiveId" clId="{01525AF4-9CFC-4414-9EAF-33FDE438DE6A}" dt="2026-04-12T21:56:00.178" v="677" actId="20577"/><pc:sldMkLst><pc:docMk/><pc:sldMk cId="0" sldId="258"/></pc:sldMkLst><pc:spChg chg="mod"><ac:chgData name="Alicia Esparza" userId="65b59e52a21d66fc" providerId="LiveId" clId="{01525AF4-9CFC-4414-9EAF-33FDE438DE6A}" dt="2026-04-12T21:56:00.178" v="677" actId="20577"/><ac:spMkLst><pc:docMk/><pc:sldMk cId="0" sldId="258"/><ac:spMk id="5" creationId="{00000000-0000-0000-0000-000000000000}"/></ac:spMkLst></pc:spChg><pc:spChg chg="mod"><ac:chgData name="Alicia Esparza" userId="65b59e52a21d66fc" providerId="LiveId" clId="{01525AF4-9CFC-4414-9EAF-33FDE438DE6A}" dt="2026-04-12T21:50:10.779" v="586" actId="20577"/><ac:spMkLst><pc:docMk/><pc:sldMk cId="0" sldId="258"/><ac:spMk id="10" creationId="{00000000-0000-0000-0000-000000000000}"/></ac:spMkLst></pc:spChg><pc:spChg chg="mod"><ac:chgData name="Alicia Esparza" userId="65b59e52a21d66fc" providerId="LiveId" clId="{01525AF4-9CFC-4414-9EAF-33FDE438DE6A}" dt="2026-04-12T21:49:01.180" v="573" actId="20577"/><ac:spMkLst><pc:docMk/><pc:sldMk cId="0" sldId="258"/><ac:spMk id="11" creationId="{00000000-0000-0000-0000-000000000000}"/></ac:spMkLst></pc:spChg><pc:spChg chg="mod"><ac:chgData name="Alicia Esparza" userId="65b59e52a21d66fc" providerId="LiveId" clId="{01525AF4-9CFC-4414-9EAF-33FDE438DE6A}" dt="2026-04-12T21:49:25.031" v="582" actId="20577"/><ac:spMkLst><pc:docMk/><pc:sldMk cId="0" sldId="258"/><ac:spMk id="12" creationId="{00000000-0000-0000-0000-000000000000}"/></ac:spMkLst></pc:spChg><pc:spChg chg="mod"><ac:chgData name="Alicia Esparza" userId="65b59e52a21d66fc" providerId="LiveId" clId="{01525AF4-9CFC-4414-9EAF-33FDE438DE6A}" dt="2026-04-12T21:52:50.181" v="630" actId="20577"/><ac:spMkLst><pc:docMk/><pc:sldMk cId="0" sldId="258"/><ac:spMk id="15" creationId="{00000000-0000-0000-0000-000000000000}"/></ac:spMkLst></pc:spChg><pc:spChg chg="mod"><ac:chgData name="Alicia Esparza" userId="65b59e52a21d66fc" providerId="LiveId" clId="{01525AF4-9CFC-4414-9EAF-33FDE438DE6A}" dt="2026-04-12T21:52:08.206" v="616" actId="20577"/><ac:spMkLst><pc:docMk/><pc:sldMk cId="0" sldId="258"/><ac:spMk id="16" creationId="{00000000-0000-0000-0000-000000000000}"/></ac:spMkLst></pc:spChg><pc:spChg chg="mod"><ac:chgData name="Alicia Esparza" userId="65b59e52a21d66fc" providerId="LiveId" clId="{01525AF4-9CFC-4414-9EAF-33FDE438DE6A}" dt="2026-04-12T21:52:36.769" v="626" actId="20577"/><ac:spMkLst><pc:docMk/><pc:sldMk cId="0" sldId="258"/><ac:spMk id="17" creationId="{00000000-0000-0000-0000-000000000000}"/></ac:spMkLst></pc:spChg><pc:spChg chg="mod"><ac:chgData name="Alicia Esparza" userId="65b59e52a21d66fc" providerId="LiveId" clId="{01525AF4-9CFC-4414-9EAF-33FDE438DE6A}" dt="2026-04-12T21:53:23.542" v="636" actId="20577"/><ac:spMkLst><pc:docMk/><pc:sldMk cId="0" sldId="258"/><ac:spMk id="21" creationId="{00000000-0000-0000-0000-000000000000}"/></ac:spMkLst></pc:spChg><pc:spChg chg="mod"><ac:chgData name="Alicia Esparza" userId="65b59e52a21d66fc" providerId="LiveId" clId="{01525AF4-9CFC-4414-9EAF-33FDE438DE6A}" dt="2026-04-12T21:53:57.299" v="644" actId="20577"/><ac:spMkLst><pc:docMk/><pc:sldMk cId="0" sldId="258"/><ac:spMk id="25" creationId="{00000000-0000-0000-0000-000000000000}"/></ac:spMkLst></pc:spChg><pc:spChg chg="mod"><ac:chgData name="Alicia Esparza" userId="65b59e52a21d66fc" providerId="LiveId" clId="{01525AF4-9CFC-4414-9EAF-33FDE438DE6A}" dt="2026-04-12T21:53:39.527" v="640" actId="20577"/><ac:spMkLst><pc:docMk/><pc:sldMk cId="0" sldId="258"/><ac:spMk id="26" creationId="{00000000-0000-0000-0000-000000000000}"/></ac:spMkLst></pc:spChg><pc:spChg chg="mod"><ac:chgData name="Alicia Esparza" userId="65b59e52a21d66fc" providerId="LiveId" clId="{01525AF4-9CFC-4414-9EAF-33FDE438DE6A}" dt="2026-04-12T21:54:21.122" v="654" actId="20577"/><ac:spMkLst><pc:docMk/><pc:sldMk cId="0" sldId="258"/><ac:spMk id="30" creationId="{00000000-0000-0000-0000-000000000000}"/></ac:spMkLst></pc:spChg><pc:spChg chg="mod"><ac:chgData name="Alicia Esparza" userId="65b59e52a21d66fc" providerId="LiveId" clId="{01525AF4-9CFC-4414-9EAF-33FDE438DE6A}" dt="2026-04-12T21:54:11.238" v="648" actId="20577"/><ac:spMkLst><pc:docMk/><pc:sldMk cId="0" sldId="258"/><ac:spMk id="31" creationId="{00000000-0000-0000-0000-000000000000}"/></ac:spMkLst></pc:spChg><pc:graphicFrameChg chg="mod"><ac:chgData name="Alicia Esparza" userId="65b59e52a21d66fc" providerId="LiveId" clId="{01525AF4-9CFC-4414-9EAF-33FDE438DE6A}" dt="2026-04-12T21:55:46.631" v="673" actId="20577"/><ac:graphicFrameMkLst><pc:docMk/><pc:sldMk cId="0" sldId="258"/><ac:graphicFrameMk id="35" creationId="{00000000-0000-0000-0000-000000000000}"/></ac:graphicFrameMkLst></pc:graphicFrameChg></pc:sldChg><pc:sldChg chg="delSp modSp mod"><pc:chgData name="Alicia Esparza" userId="65b59e52a21d66fc" providerId="LiveId" clId="{01525AF4-9CFC-4414-9EAF-33FDE438DE6A}" dt="2026-04-12T22:03:59.039" v="755" actId="20577"/><pc:sldMkLst><pc:docMk/><pc:sldMk cId="0" sldId="259"/></pc:sldMkLst><pc:spChg chg="mod"><ac:chgData name="Alicia Esparza" userId="65b59e52a21d66fc" providerId="LiveId" clId="{01525AF4-9CFC-4414-9EAF-33FDE438DE6A}" dt="2026-04-12T21:56:27.822" v="681" actId="20577"/><ac:spMkLst><pc:docMk/><pc:sldMk cId="0" sldId="259"/><ac:spMk id="5" creationId="{00000000-0000-0000-0000-000000000000}"/></ac:spMkLst></pc:spChg><pc:spChg chg="mod"><ac:chgData name="Alicia Esparza" userId="65b59e52a21d66fc" providerId="LiveId" clId="{01525AF4-9CFC-4414-9EAF-33FDE438DE6A}" dt="2026-04-12T22:02:06.202" v="720" actId="20577"/><ac:spMkLst><pc:docMk/><pc:sldMk cId="0" sldId="259"/><ac:spMk id="8" creationId="{00000000-0000-0000-0000-000000000000}"/></ac:spMkLst></pc:spChg><pc:spChg chg="mod"><ac:chgData name="Alicia Esparza" userId="65b59e52a21d66fc" providerId="LiveId" clId="{01525AF4-9CFC-4414-9EAF-33FDE438DE6A}" dt="2026-04-12T22:03:08.236" v="736" actId="20577"/><ac:spMkLst><pc:docMk/><pc:sldMk cId="0" sldId="259"/><ac:spMk id="9" creationId="{00000000-0000-0000-0000-000000000000}"/></ac:spMkLst></pc:spChg><pc:spChg chg="mod"><ac:chgData name="Alicia Esparza" userId="65b59e52a21d66fc" providerId="LiveId" clId="{01525AF4-9CFC-4414-9EAF-33FDE438DE6A}" dt="2026-04-12T22:03:51.936" v="751" actId="20577"/><ac:spMkLst><pc:docMk/><pc:sldMk cId="0" sldId="259"/><ac:spMk id="10" creationId="{00000000-0000-0000-0000-000000000000}"/></ac:spMkLst></pc:spChg><pc:spChg chg="mod"><ac:chgData name="Alicia Esparza" userId="65b59e52a21d66fc" providerId="LiveId" clId="{01525AF4-9CFC-4414-9EAF-33FDE438DE6A}" dt="2026-04-12T21:58:43.021" v="693" actId="20577"/><ac:spMkLst><pc:docMk/><pc:sldMk cId="0" sldId="259"/><ac:spMk id="12" creationId="{00000000-0000-0000-0000-000000000000}"/></ac:spMkLst></pc:spChg><pc:spChg chg="del mod"><ac:chgData name="Alicia Esparza" userId="65b59e52a21d66fc" providerId="LiveId" clId="{01525AF4-9CFC-4414-9EAF-33FDE438DE6A}" dt="2026-04-12T21:58:28.391" v="689" actId="478"/><ac:spMkLst><pc:docMk/><pc:sldMk cId="0" sldId="259"/><ac:spMk id="13" creationId="{00000000-0000-0000-0000-000000000000}"/></ac:spMkLst></pc:spChg><pc:spChg chg="mod"><ac:chgData name="Alicia Esparza" userId="65b59e52a21d66fc" providerId="LiveId" clId="{01525AF4-9CFC-4414-9EAF-33FDE438DE6A}" dt="2026-04-12T22:02:16.018" v="724" actId="20577"/><ac:spMkLst><pc:docMk/><pc:sldMk cId="0" sldId="259"/><ac:spMk id="16" creationId="{00000000-0000-0000-0000-000000000000}"/></ac:spMkLst></pc:spChg><pc:spChg chg="mod"><ac:chgData name="Alicia Esparza" userId="65b59e52a21d66fc" providerId="LiveId" clId="{01525AF4-9CFC-4414-9EAF-33FDE438DE6A}" dt="2026-04-12T22:03:23.741" v="741" actId="20577"/><ac:spMkLst><pc:docMk/><pc:sldMk cId="0" sldId="259"/><ac:spMk id="17" creationId="{00000000-0000-0000-0000-000000000000}"/></ac:spMkLst></pc:spChg><pc:spChg chg="mod"><ac:chgData name="Alicia Esparza" userId="65b59e52a21d66fc" providerId="LiveId" clId="{01525AF4-9CFC-4414-9EAF-33FDE438DE6A}" dt="2026-04-12T22:03:59.039" v="755" actId="20577"/><ac:spMkLst><pc:docMk/><pc:sldMk cId="0" sldId="259"/><ac:spMk id="18" creationId="{00000000-0000-0000-0000-000000000000}"/></ac:spMkLst></pc:spChg><pc:spChg chg="mod"><ac:chgData name="Alicia Esparza" userId="65b59e52a21d66fc" providerId="LiveId" clId="{01525AF4-9CFC-4414-9EAF-33FDE438DE6A}" dt="2026-04-12T22:00:33.761" v="706" actId="20577"/><ac:spMkLst><pc:docMk/><pc:sldMk cId="0" sldId="259"/><ac:spMk id="20" creationId="{00000000-0000-0000-0000-000000000000}"/></ac:spMkLst></pc:spChg><pc:spChg chg="del"><ac:chgData name="Alicia Esparza" userId="65b59e52a21d66fc" providerId="LiveId" clId="{01525AF4-9CFC-4414-9EAF-33FDE438DE6A}" dt="2026-04-12T22:00:43.152" v="707" actId="478"/><ac:spMkLst><pc:docMk/><pc:sldMk cId="0" sldId="259"/><ac:spMk id="21" creationId="{00000000-0000-0000-0000-000000000000}"/></ac:spMkLst></pc:spChg><pc:spChg chg="mod"><ac:chgData name="Alicia Esparza" userId="65b59e52a21d66fc" providerId="LiveId" clId="{01525AF4-9CFC-4414-9EAF-33FDE438DE6A}" dt="2026-04-12T22:02:25.057" v="726" actId="20577"/><ac:spMkLst><pc:docMk/><pc:sldMk cId="0" sldId="259"/><ac:spMk id="24" creationId="{00000000-0000-0000-0000-000000000000}"/></ac:spMkLst></pc:spChg><pc:spChg chg="mod"><ac:chgData name="Alicia Esparza" userId="65b59e52a21d66fc" providerId="LiveId" clId="{01525AF4-9CFC-4414-9EAF-33FDE438DE6A}" dt="2026-04-12T22:01:09.752" v="715" actId="20577"/><ac:spMkLst><pc:docMk/><pc:sldMk cId="0" sldId="259"/><ac:spMk id="28" creationId="{00000000-0000-0000-0000-000000000000}"/></ac:spMkLst></pc:spChg><pc:spChg chg="del"><ac:chgData name="Alicia Esparza" userId="65b59e52a21d66fc" providerId="LiveId" clId="{01525AF4-9CFC-4414-9EAF-33FDE438DE6A}" dt="2026-04-12T22:01:17.866" v="716" actId="478"/><ac:spMkLst><pc:docMk/><pc:sldMk cId="0" sldId="259"/><ac:spMk id="29" creationId="{00000000-0000-0000-0000-000000000000}"/></ac:spMkLst></pc:spChg></pc:sldChg><pc:sldChg chg="delSp modSp del mod"><pc:chgData name="Alicia Esparza" userId="65b59e52a21d66fc" providerId="LiveId" clId="{01525AF4-9CFC-4414-9EAF-33FDE438DE6A}" dt="2026-04-12T22:59:25.156" v="758" actId="47"/><pc:sldMkLst><pc:docMk/><pc:sldMk cId="0" sldId="260"/></pc:sldMkLst><pc:spChg chg="mod"><ac:chgData name="Alicia Esparza" userId="65b59e52a21d66fc" providerId="LiveId" clId="{01525AF4-9CFC-4414-9EAF-33FDE438DE6A}" dt="2026-04-12T22:58:43.453" v="757" actId="1076"/><ac:spMkLst><pc:docMk/><pc:sldMk cId="0" sldId="260"/><ac:spMk id="4" creationId="{00000000-0000-0000-0000-000000000000}"/></ac:spMkLst></pc:spChg><pc:spChg chg="del"><ac:chgData name="Alicia Esparza" userId="65b59e52a21d66fc" providerId="LiveId" clId="{01525AF4-9CFC-4414-9EAF-33FDE438DE6A}" dt="2026-04-12T22:58:38.920" v="756" actId="478"/><ac:spMkLst><pc:docMk/><pc:sldMk cId="0" sldId="260"/><ac:spMk id="5" creationId="{00000000-0000-0000-0000-000000000000}"/></ac:spMkLst></pc:spChg></pc:sldChg><pc:sldChg chg="del"><pc:chgData name="Alicia Esparza" userId="65b59e52a21d66fc" providerId="LiveId" clId="{01525AF4-9CFC-4414-9EAF-33FDE438DE6A}" dt="2026-04-08T10:28:56.407" v="154" actId="47"/><pc:sldMkLst><pc:docMk/><pc:sldMk cId="0" sldId="262"/></pc:sldMkLst></pc:sldChg><pc:sldChg chg="del"><pc:chgData name="Alicia Esparza" userId="65b59e52a21d66fc" providerId="LiveId" clId="{01525AF4-9CFC-4414-9EAF-33FDE438DE6A}" dt="2026-04-12T23:11:47.376" v="859" actId="47"/><pc:sldMkLst><pc:docMk/><pc:sldMk cId="0" sldId="263"/></pc:sldMkLst></pc:sldChg><pc:sldChg chg="del"><pc:chgData name="Alicia Esparza" userId="65b59e52a21d66fc" providerId="LiveId" clId="{01525AF4-9CFC-4414-9EAF-33FDE438DE6A}" dt="2026-04-12T23:00:42.709" v="760" actId="47"/><pc:sldMkLst><pc:docMk/><pc:sldMk cId="1206527388" sldId="264"/></pc:sldMkLst></pc:sldChg><pc:sldChg chg="del"><pc:chgData name="Alicia Esparza" userId="65b59e52a21d66fc" providerId="LiveId" clId="{01525AF4-9CFC-4414-9EAF-33FDE438DE6A}" dt="2026-04-12T23:00:47.419" v="763" actId="47"/><pc:sldMkLst><pc:docMk/><pc:sldMk cId="4131611713" sldId="265"/></pc:sldMkLst></pc:sldChg><pc:sldChg chg="del"><pc:chgData name="Alicia Esparza" userId="65b59e52a21d66fc" providerId="LiveId" clId="{01525AF4-9CFC-4414-9EAF-33FDE438DE6A}" dt="2026-04-12T23:00:46.010" v="762" actId="47"/><pc:sldMkLst><pc:docMk/><pc:sldMk cId="2851103926" sldId="267"/></pc:sldMkLst></pc:sldChg><pc:sldChg chg="modSp mod"><pc:chgData name="Alicia Esparza" userId="65b59e52a21d66fc" providerId="LiveId" clId="{01525AF4-9CFC-4414-9EAF-33FDE438DE6A}" dt="2026-04-12T18:12:18.614" v="403" actId="403"/><pc:sldMkLst><pc:docMk/><pc:sldMk cId="740225277" sldId="269"/></pc:sldMkLst><pc:spChg chg="mod"><ac:chgData name="Alicia Esparza" userId="65b59e52a21d66fc" providerId="LiveId" clId="{01525AF4-9CFC-4414-9EAF-33FDE438DE6A}" dt="2026-04-12T18:12:09.928" v="402" actId="14100"/><ac:spMkLst><pc:docMk/><pc:sldMk cId="740225277" sldId="269"/><ac:spMk id="3" creationId="{00000000-0000-0000-0000-000000000000}"/></ac:spMkLst></pc:spChg><pc:spChg chg="mod"><ac:chgData name="Alicia Esparza" userId="65b59e52a21d66fc" providerId="LiveId" clId="{01525AF4-9CFC-4414-9EAF-33FDE438DE6A}" dt="2026-04-12T18:12:06.267" v="401" actId="1076"/><ac:spMkLst><pc:docMk/><pc:sldMk cId="740225277" sldId="269"/><ac:spMk id="5" creationId="{00000000-0000-0000-0000-000000000000}"/></ac:spMkLst></pc:spChg><pc:spChg chg="mod"><ac:chgData name="Alicia Esparza" userId="65b59e52a21d66fc" providerId="LiveId" clId="{01525AF4-9CFC-4414-9EAF-33FDE438DE6A}" dt="2026-04-12T18:12:18.614" v="403" actId="403"/><ac:spMkLst><pc:docMk/><pc:sldMk cId="740225277" sldId="269"/><ac:spMk id="6" creationId="{00000000-0000-0000-0000-000000000000}"/></ac:spMkLst></pc:spChg><pc:picChg chg="mod"><ac:chgData name="Alicia Esparza" userId="65b59e52a21d66fc" providerId="LiveId" clId="{01525AF4-9CFC-4414-9EAF-33FDE438DE6A}" dt="2026-04-12T18:11:23.698" v="394" actId="14100"/><ac:picMkLst><pc:docMk/><pc:sldMk cId="740225277" sldId="269"/><ac:picMk id="2" creationId="{00000000-0000-0000-0000-000000000000}"/></ac:picMkLst></pc:picChg></pc:sldChg><pc:sldChg chg="del"><pc:chgData name="Alicia Esparza" userId="65b59e52a21d66fc" providerId="LiveId" clId="{01525AF4-9CFC-4414-9EAF-33FDE438DE6A}" dt="2026-04-13T01:23:27.187" v="945" actId="47"/><pc:sldMkLst><pc:docMk/><pc:sldMk cId="0" sldId="337"/></pc:sldMkLst></pc:sldChg><pc:sldChg chg="modSp mod"><pc:chgData name="Alicia Esparza" userId="65b59e52a21d66fc" providerId="LiveId" clId="{01525AF4-9CFC-4414-9EAF-33FDE438DE6A}" dt="2026-04-13T02:10:41.719" v="1040" actId="14100"/><pc:sldMkLst><pc:docMk/><pc:sldMk cId="2267351596" sldId="337"/></pc:sldMkLst><pc:spChg chg="mod"><ac:chgData name="Alicia Esparza" userId="65b59e52a21d66fc" providerId="LiveId" clId="{01525AF4-9CFC-4414-9EAF-33FDE438DE6A}" dt="2026-04-13T02:10:41.719" v="1040" actId="14100"/><ac:spMkLst><pc:docMk/><pc:sldMk cId="2267351596" sldId="337"/><ac:spMk id="13" creationId="{442201AF-C917-1616-A0BC-878E3F47A53B}"/></ac:spMkLst></pc:spChg></pc:sldChg><pc:sldChg chg="del"><pc:chgData name="Alicia Esparza" userId="65b59e52a21d66fc" providerId="LiveId" clId="{01525AF4-9CFC-4414-9EAF-33FDE438DE6A}" dt="2026-04-13T01:25:02.576" v="946" actId="47"/><pc:sldMkLst><pc:docMk/><pc:sldMk cId="0" sldId="339"/></pc:sldMkLst></pc:sldChg><pc:sldChg chg="modSp mod ord"><pc:chgData name="Alicia Esparza" userId="65b59e52a21d66fc" providerId="LiveId" clId="{01525AF4-9CFC-4414-9EAF-33FDE438DE6A}" dt="2026-04-12T23:06:27.061" v="805"/><pc:sldMkLst><pc:docMk/><pc:sldMk cId="1391514263" sldId="340"/></pc:sldMkLst><pc:spChg chg="mod"><ac:chgData name="Alicia Esparza" userId="65b59e52a21d66fc" providerId="LiveId" clId="{01525AF4-9CFC-4414-9EAF-33FDE438DE6A}" dt="2026-04-08T10:20:56.710" v="28" actId="27636"/><ac:spMkLst><pc:docMk/><pc:sldMk cId="1391514263" sldId="340"/><ac:spMk id="20" creationId="{00000000-0000-0000-0000-000000000000}"/></ac:spMkLst></pc:spChg><pc:spChg chg="mod"><ac:chgData name="Alicia Esparza" userId="65b59e52a21d66fc" providerId="LiveId" clId="{01525AF4-9CFC-4414-9EAF-33FDE438DE6A}" dt="2026-04-12T23:04:20.359" v="793" actId="20577"/><ac:spMkLst><pc:docMk/><pc:sldMk cId="1391514263" sldId="340"/><ac:spMk id="21" creationId="{00000000-0000-0000-0000-000000000000}"/></ac:spMkLst></pc:spChg><pc:spChg chg="mod"><ac:chgData name="Alicia Esparza" userId="65b59e52a21d66fc" providerId="LiveId" clId="{01525AF4-9CFC-4414-9EAF-33FDE438DE6A}" dt="2026-04-12T23:05:16.231" v="799" actId="20577"/><ac:spMkLst><pc:docMk/><pc:sldMk cId="1391514263" sldId="340"/><ac:spMk id="22" creationId="{00000000-0000-0000-0000-000000000000}"/></ac:spMkLst></pc:spChg><pc:spChg chg="mod"><ac:chgData name="Alicia Esparza" userId="65b59e52a21d66fc" providerId="LiveId" clId="{01525AF4-9CFC-4414-9EAF-33FDE438DE6A}" dt="2026-04-12T23:05:24.577" v="803" actId="20577"/><ac:spMkLst><pc:docMk/><pc:sldMk cId="1391514263" sldId="340"/><ac:spMk id="23" creationId="{00000000-0000-0000-0000-000000000000}"/></ac:spMkLst></pc:spChg><pc:spChg chg="mod"><ac:chgData name="Alicia Esparza" userId="65b59e52a21d66fc" providerId="LiveId" clId="{01525AF4-9CFC-4414-9EAF-33FDE438DE6A}" dt="2026-04-08T10:20:56.698" v="25" actId="27636"/><ac:spMkLst><pc:docMk/><pc:sldMk cId="1391514263" sldId="340"/><ac:spMk id="25" creationId="{00000000-0000-0000-0000-000000000000}"/></ac:spMkLst></pc:spChg><pc:spChg chg="mod"><ac:chgData name="Alicia Esparza" userId="65b59e52a21d66fc" providerId="LiveId" clId="{01525AF4-9CFC-4414-9EAF-33FDE438DE6A}" dt="2026-04-08T10:20:56.698" v="27" actId="27636"/><ac:spMkLst><pc:docMk/><pc:sldMk cId="1391514263" sldId="340"/><ac:spMk id="26" creationId="{00000000-0000-0000-0000-000000000000}"/></ac:spMkLst></pc:spChg><pc:graphicFrameChg chg="modGraphic"><ac:chgData name="Alicia Esparza" userId="65b59e52a21d66fc" providerId="LiveId" clId="{01525AF4-9CFC-4414-9EAF-33FDE438DE6A}" dt="2026-04-08T10:27:12.537" v="130" actId="403"/><ac:graphicFrameMkLst><pc:docMk/><pc:sldMk cId="1391514263" sldId="340"/><ac:graphicFrameMk id="50" creationId="{00000000-0000-0000-0000-000000000000}"/></ac:graphicFrameMkLst></pc:graphicFrameChg></pc:sldChg><pc:sldChg chg="del"><pc:chgData name="Alicia Esparza" userId="65b59e52a21d66fc" providerId="LiveId" clId="{01525AF4-9CFC-4414-9EAF-33FDE438DE6A}" dt="2026-04-13T01:28:50.260" v="952" actId="47"/><pc:sldMkLst><pc:docMk/><pc:sldMk cId="0" sldId="341"/></pc:sldMkLst></pc:sldChg><pc:sldChg chg="modSp del mod"><pc:chgData name="Alicia Esparza" userId="65b59e52a21d66fc" providerId="LiveId" clId="{01525AF4-9CFC-4414-9EAF-33FDE438DE6A}" dt="2026-04-06T13:48:50.472" v="4" actId="47"/><pc:sldMkLst><pc:docMk/><pc:sldMk cId="0" sldId="342"/></pc:sldMkLst><pc:spChg chg="mod"><ac:chgData name="Alicia Esparza" userId="65b59e52a21d66fc" providerId="LiveId" clId="{01525AF4-9CFC-4414-9EAF-33FDE438DE6A}" dt="2026-04-06T13:47:28.781" v="1" actId="20577"/><ac:spMkLst><pc:docMk/><pc:sldMk cId="0" sldId="342"/><ac:spMk id="26" creationId="{00000000-0000-0000-0000-000000000000}"/></ac:spMkLst></pc:spChg><pc:spChg chg="mod"><ac:chgData name="Alicia Esparza" userId="65b59e52a21d66fc" providerId="LiveId" clId="{01525AF4-9CFC-4414-9EAF-33FDE438DE6A}" dt="2026-04-06T13:47:36.797" v="3" actId="20577"/><ac:spMkLst><pc:docMk/><pc:sldMk cId="0" sldId="342"/><ac:spMk id="29" creationId="{00000000-0000-0000-0000-000000000000}"/></ac:spMkLst></pc:spChg></pc:sldChg><pc:sldChg chg="delSp modSp mod ord"><pc:chgData name="Alicia Esparza" userId="65b59e52a21d66fc" providerId="LiveId" clId="{01525AF4-9CFC-4414-9EAF-33FDE438DE6A}" dt="2026-04-12T23:10:29.653" v="842" actId="20577"/><pc:sldMkLst><pc:docMk/><pc:sldMk cId="2456494035" sldId="342"/></pc:sldMkLst><pc:spChg chg="mod"><ac:chgData name="Alicia Esparza" userId="65b59e52a21d66fc" providerId="LiveId" clId="{01525AF4-9CFC-4414-9EAF-33FDE438DE6A}" dt="2026-04-08T10:20:56.730" v="38" actId="27636"/><ac:spMkLst><pc:docMk/><pc:sldMk cId="2456494035" sldId="342"/><ac:spMk id="20" creationId="{00000000-0000-0000-0000-000000000000}"/></ac:spMkLst></pc:spChg><pc:spChg chg="mod"><ac:chgData name="Alicia Esparza" userId="65b59e52a21d66fc" providerId="LiveId" clId="{01525AF4-9CFC-4414-9EAF-33FDE438DE6A}" dt="2026-04-12T23:09:55.020" v="834" actId="20577"/><ac:spMkLst><pc:docMk/><pc:sldMk cId="2456494035" sldId="342"/><ac:spMk id="21" creationId="{00000000-0000-0000-0000-000000000000}"/></ac:spMkLst></pc:spChg><pc:spChg chg="mod"><ac:chgData name="Alicia Esparza" userId="65b59e52a21d66fc" providerId="LiveId" clId="{01525AF4-9CFC-4414-9EAF-33FDE438DE6A}" dt="2026-04-12T23:10:29.653" v="842" actId="20577"/><ac:spMkLst><pc:docMk/><pc:sldMk cId="2456494035" sldId="342"/><ac:spMk id="22" creationId="{00000000-0000-0000-0000-000000000000}"/></ac:spMkLst></pc:spChg><pc:spChg chg="mod"><ac:chgData name="Alicia Esparza" userId="65b59e52a21d66fc" providerId="LiveId" clId="{01525AF4-9CFC-4414-9EAF-33FDE438DE6A}" dt="2026-04-12T23:10:11.142" v="838" actId="20577"/><ac:spMkLst><pc:docMk/><pc:sldMk cId="2456494035" sldId="342"/><ac:spMk id="23" creationId="{00000000-0000-0000-0000-000000000000}"/></ac:spMkLst></pc:spChg><pc:spChg chg="del mod"><ac:chgData name="Alicia Esparza" userId="65b59e52a21d66fc" providerId="LiveId" clId="{01525AF4-9CFC-4414-9EAF-33FDE438DE6A}" dt="2026-04-12T23:07:50.534" v="820" actId="478"/><ac:spMkLst><pc:docMk/><pc:sldMk cId="2456494035" sldId="342"/><ac:spMk id="25" creationId="{00000000-0000-0000-0000-000000000000}"/></ac:spMkLst></pc:spChg><pc:spChg chg="mod"><ac:chgData name="Alicia Esparza" userId="65b59e52a21d66fc" providerId="LiveId" clId="{01525AF4-9CFC-4414-9EAF-33FDE438DE6A}" dt="2026-04-08T10:20:56.730" v="40" actId="27636"/><ac:spMkLst><pc:docMk/><pc:sldMk cId="2456494035" sldId="342"/><ac:spMk id="26" creationId="{00000000-0000-0000-0000-000000000000}"/></ac:spMkLst></pc:spChg><pc:graphicFrameChg chg="modGraphic"><ac:chgData name="Alicia Esparza" userId="65b59e52a21d66fc" providerId="LiveId" clId="{01525AF4-9CFC-4414-9EAF-33FDE438DE6A}" dt="2026-04-08T10:28:09.268" v="145" actId="404"/><ac:graphicFrameMkLst><pc:docMk/><pc:sldMk cId="2456494035" sldId="342"/><ac:graphicFrameMk id="50" creationId="{00000000-0000-0000-0000-000000000000}"/></ac:graphicFrameMkLst></pc:graphicFrameChg></pc:sldChg><pc:sldChg chg="modSp del mod"><pc:chgData name="Alicia Esparza" userId="65b59e52a21d66fc" providerId="LiveId" clId="{01525AF4-9CFC-4414-9EAF-33FDE438DE6A}" dt="2026-04-13T02:12:54.504" v="1056" actId="14734"/><pc:sldMkLst><pc:docMk/><pc:sldMk cId="0" sldId="343"/></pc:sldMkLst><pc:spChg chg="mod"><ac:chgData name="Alicia Esparza" userId="65b59e52a21d66fc" providerId="LiveId" clId="{01525AF4-9CFC-4414-9EAF-33FDE438DE6A}" dt="2026-04-13T02:12:42.762" v="1055" actId="14100"/><ac:spMkLst><pc:docMk/><pc:sldMk cId="0" sldId="343"/><ac:spMk id="7" creationId="{00000000-0000-0000-0000-000000000000}"/></ac:spMkLst></pc:spChg><pc:graphicFrameChg chg="mod modGraphic"><ac:chgData name="Alicia Esparza" userId="65b59e52a21d66fc" providerId="LiveId" clId="{01525AF4-9CFC-4414-9EAF-33FDE438DE6A}" dt="2026-04-13T02:12:54.504" v="1056" actId="14734"/><ac:graphicFrameMkLst><pc:docMk/><pc:sldMk cId="0" sldId="343"/><ac:graphicFrameMk id="6" creationId="{00000000-0000-0000-0000-000000000000}"/></ac:graphicFrameMkLst></pc:graphicFrameChg></pc:sldChg><pc:sldChg chg="del"><pc:chgData name="Alicia Esparza" userId="65b59e52a21d66fc" providerId="LiveId" clId="{01525AF4-9CFC-4414-9EAF-33FDE438DE6A}" dt="2026-04-13T01:33:04.491" v="959" actId="47"/><pc:sldMkLst><pc:docMk/><pc:sldMk cId="0" sldId="344"/></pc:sldMkLst></pc:sldChg><pc:sldChg chg="addSp delSp modSp mod"><pc:chgData name="Alicia Esparza" userId="65b59e52a21d66fc" providerId="LiveId" clId="{01525AF4-9CFC-4414-9EAF-33FDE438DE6A}" dt="2026-04-12T23:08:32.548" v="824" actId="478"/><pc:sldMkLst><pc:docMk/><pc:sldMk cId="1183928205" sldId="345"/></pc:sldMkLst><pc:spChg chg="mod"><ac:chgData name="Alicia Esparza" userId="65b59e52a21d66fc" providerId="LiveId" clId="{01525AF4-9CFC-4414-9EAF-33FDE438DE6A}" dt="2026-04-08T13:05:49.976" v="173" actId="14100"/><ac:spMkLst><pc:docMk/><pc:sldMk cId="1183928205" sldId="345"/><ac:spMk id="10" creationId="{00000000-0000-0000-0000-000000000000}"/></ac:spMkLst></pc:spChg><pc:spChg chg="mod"><ac:chgData name="Alicia Esparza" userId="65b59e52a21d66fc" providerId="LiveId" clId="{01525AF4-9CFC-4414-9EAF-33FDE438DE6A}" dt="2026-04-08T13:05:54.816" v="174" actId="403"/><ac:spMkLst><pc:docMk/><pc:sldMk cId="1183928205" sldId="345"/><ac:spMk id="11" creationId="{00000000-0000-0000-0000-000000000000}"/></ac:spMkLst></pc:spChg><pc:spChg chg="mod"><ac:chgData name="Alicia Esparza" userId="65b59e52a21d66fc" providerId="LiveId" clId="{01525AF4-9CFC-4414-9EAF-33FDE438DE6A}" dt="2026-04-08T13:04:19.808" v="169" actId="403"/><ac:spMkLst><pc:docMk/><pc:sldMk cId="1183928205" sldId="345"/><ac:spMk id="20" creationId="{00000000-0000-0000-0000-000000000000}"/></ac:spMkLst></pc:spChg><pc:spChg chg="mod"><ac:chgData name="Alicia Esparza" userId="65b59e52a21d66fc" providerId="LiveId" clId="{01525AF4-9CFC-4414-9EAF-33FDE438DE6A}" dt="2026-04-12T23:03:08.019" v="787" actId="20577"/><ac:spMkLst><pc:docMk/><pc:sldMk cId="1183928205" sldId="345"/><ac:spMk id="21" creationId="{00000000-0000-0000-0000-000000000000}"/></ac:spMkLst></pc:spChg><pc:spChg chg="mod"><ac:chgData name="Alicia Esparza" userId="65b59e52a21d66fc" providerId="LiveId" clId="{01525AF4-9CFC-4414-9EAF-33FDE438DE6A}" dt="2026-04-12T23:02:52.096" v="777" actId="20577"/><ac:spMkLst><pc:docMk/><pc:sldMk cId="1183928205" sldId="345"/><ac:spMk id="22" creationId="{00000000-0000-0000-0000-000000000000}"/></ac:spMkLst></pc:spChg><pc:spChg chg="mod"><ac:chgData name="Alicia Esparza" userId="65b59e52a21d66fc" providerId="LiveId" clId="{01525AF4-9CFC-4414-9EAF-33FDE438DE6A}" dt="2026-04-12T23:02:36.762" v="767" actId="20577"/><ac:spMkLst><pc:docMk/><pc:sldMk cId="1183928205" sldId="345"/><ac:spMk id="23" creationId="{00000000-0000-0000-0000-000000000000}"/></ac:spMkLst></pc:spChg><pc:spChg chg="del mod"><ac:chgData name="Alicia Esparza" userId="65b59e52a21d66fc" providerId="LiveId" clId="{01525AF4-9CFC-4414-9EAF-33FDE438DE6A}" dt="2026-04-12T23:08:32.548" v="824" actId="478"/><ac:spMkLst><pc:docMk/><pc:sldMk cId="1183928205" sldId="345"/><ac:spMk id="25" creationId="{00000000-0000-0000-0000-000000000000}"/></ac:spMkLst></pc:spChg><pc:spChg chg="mod"><ac:chgData name="Alicia Esparza" userId="65b59e52a21d66fc" providerId="LiveId" clId="{01525AF4-9CFC-4414-9EAF-33FDE438DE6A}" dt="2026-04-08T10:22:22.867" v="59" actId="1076"/><ac:spMkLst><pc:docMk/><pc:sldMk cId="1183928205" sldId="345"/><ac:spMk id="26" creationId="{00000000-0000-0000-0000-000000000000}"/></ac:spMkLst></pc:spChg><pc:grpChg chg="add mod"><ac:chgData name="Alicia Esparza" userId="65b59e52a21d66fc" providerId="LiveId" clId="{01525AF4-9CFC-4414-9EAF-33FDE438DE6A}" dt="2026-04-08T13:04:45.544" v="170" actId="1076"/><ac:grpSpMkLst><pc:docMk/><pc:sldMk cId="1183928205" sldId="345"/><ac:grpSpMk id="2" creationId="{63A307F3-49B5-2783-97F0-A9FD999E30E3}"/></ac:grpSpMkLst></pc:grpChg><pc:graphicFrameChg chg="mod modGraphic"><ac:chgData name="Alicia Esparza" userId="65b59e52a21d66fc" providerId="LiveId" clId="{01525AF4-9CFC-4414-9EAF-33FDE438DE6A}" dt="2026-04-08T13:03:51.525" v="158" actId="1076"/><ac:graphicFrameMkLst><pc:docMk/><pc:sldMk cId="1183928205" sldId="345"/><ac:graphicFrameMk id="50" creationId="{00000000-0000-0000-0000-000000000000}"/></ac:graphicFrameMkLst></pc:graphicFrameChg></pc:sldChg><pc:sldChg chg="delSp modSp mod"><pc:chgData name="Alicia Esparza" userId="65b59e52a21d66fc" providerId="LiveId" clId="{01525AF4-9CFC-4414-9EAF-33FDE438DE6A}" dt="2026-04-12T23:08:24.631" v="823" actId="478"/><pc:sldMkLst><pc:docMk/><pc:sldMk cId="1066928034" sldId="346"/></pc:sldMkLst><pc:spChg chg="mod"><ac:chgData name="Alicia Esparza" userId="65b59e52a21d66fc" providerId="LiveId" clId="{01525AF4-9CFC-4414-9EAF-33FDE438DE6A}" dt="2026-04-08T10:20:56.677" v="16" actId="27636"/><ac:spMkLst><pc:docMk/><pc:sldMk cId="1066928034" sldId="346"/><ac:spMk id="20" creationId="{00000000-0000-0000-0000-000000000000}"/></ac:spMkLst></pc:spChg><pc:spChg chg="mod"><ac:chgData name="Alicia Esparza" userId="65b59e52a21d66fc" providerId="LiveId" clId="{01525AF4-9CFC-4414-9EAF-33FDE438DE6A}" dt="2026-04-08T10:20:56.675" v="14" actId="27636"/><ac:spMkLst><pc:docMk/><pc:sldMk cId="1066928034" sldId="346"/><ac:spMk id="21" creationId="{00000000-0000-0000-0000-000000000000}"/></ac:spMkLst></pc:spChg><pc:spChg chg="mod"><ac:chgData name="Alicia Esparza" userId="65b59e52a21d66fc" providerId="LiveId" clId="{01525AF4-9CFC-4414-9EAF-33FDE438DE6A}" dt="2026-04-08T10:20:56.673" v="13" actId="27636"/><ac:spMkLst><pc:docMk/><pc:sldMk cId="1066928034" sldId="346"/><ac:spMk id="22" creationId="{00000000-0000-0000-0000-000000000000}"/></ac:spMkLst></pc:spChg><pc:spChg chg="mod"><ac:chgData name="Alicia Esparza" userId="65b59e52a21d66fc" providerId="LiveId" clId="{01525AF4-9CFC-4414-9EAF-33FDE438DE6A}" dt="2026-04-08T10:20:56.675" v="15" actId="27636"/><ac:spMkLst><pc:docMk/><pc:sldMk cId="1066928034" sldId="346"/><ac:spMk id="23" creationId="{00000000-0000-0000-0000-000000000000}"/></ac:spMkLst></pc:spChg><pc:spChg chg="del mod"><ac:chgData name="Alicia Esparza" userId="65b59e52a21d66fc" providerId="LiveId" clId="{01525AF4-9CFC-4414-9EAF-33FDE438DE6A}" dt="2026-04-12T23:08:24.631" v="823" actId="478"/><ac:spMkLst><pc:docMk/><pc:sldMk cId="1066928034" sldId="346"/><ac:spMk id="25" creationId="{00000000-0000-0000-0000-000000000000}"/></ac:spMkLst></pc:spChg><pc:spChg chg="mod"><ac:chgData name="Alicia Esparza" userId="65b59e52a21d66fc" providerId="LiveId" clId="{01525AF4-9CFC-4414-9EAF-33FDE438DE6A}" dt="2026-04-08T10:26:26.181" v="119" actId="403"/><ac:spMkLst><pc:docMk/><pc:sldMk cId="1066928034" sldId="346"/><ac:spMk id="26" creationId="{00000000-0000-0000-0000-000000000000}"/></ac:spMkLst></pc:spChg><pc:graphicFrameChg chg="modGraphic"><ac:chgData name="Alicia Esparza" userId="65b59e52a21d66fc" providerId="LiveId" clId="{01525AF4-9CFC-4414-9EAF-33FDE438DE6A}" dt="2026-04-08T10:26:00.297" v="107" actId="403"/><ac:graphicFrameMkLst><pc:docMk/><pc:sldMk cId="1066928034" sldId="346"/><ac:graphicFrameMk id="50" creationId="{00000000-0000-0000-0000-000000000000}"/></ac:graphicFrameMkLst></pc:graphicFrameChg></pc:sldChg><pc:sldChg chg="delSp modSp mod"><pc:chgData name="Alicia Esparza" userId="65b59e52a21d66fc" providerId="LiveId" clId="{01525AF4-9CFC-4414-9EAF-33FDE438DE6A}" dt="2026-04-12T23:08:55.034" v="825" actId="478"/><pc:sldMkLst><pc:docMk/><pc:sldMk cId="807981159" sldId="347"/></pc:sldMkLst><pc:spChg chg="mod"><ac:chgData name="Alicia Esparza" userId="65b59e52a21d66fc" providerId="LiveId" clId="{01525AF4-9CFC-4414-9EAF-33FDE438DE6A}" dt="2026-04-08T10:20:56.691" v="21" actId="27636"/><ac:spMkLst><pc:docMk/><pc:sldMk cId="807981159" sldId="347"/><ac:spMk id="20" creationId="{00000000-0000-0000-0000-000000000000}"/></ac:spMkLst></pc:spChg><pc:spChg chg="mod"><ac:chgData name="Alicia Esparza" userId="65b59e52a21d66fc" providerId="LiveId" clId="{01525AF4-9CFC-4414-9EAF-33FDE438DE6A}" dt="2026-04-08T10:20:56.689" v="19" actId="27636"/><ac:spMkLst><pc:docMk/><pc:sldMk cId="807981159" sldId="347"/><ac:spMk id="21" creationId="{00000000-0000-0000-0000-000000000000}"/></ac:spMkLst></pc:spChg><pc:spChg chg="mod"><ac:chgData name="Alicia Esparza" userId="65b59e52a21d66fc" providerId="LiveId" clId="{01525AF4-9CFC-4414-9EAF-33FDE438DE6A}" dt="2026-04-08T10:20:56.687" v="17" actId="27636"/><ac:spMkLst><pc:docMk/><pc:sldMk cId="807981159" sldId="347"/><ac:spMk id="22" creationId="{00000000-0000-0000-0000-000000000000}"/></ac:spMkLst></pc:spChg><pc:spChg chg="mod"><ac:chgData name="Alicia Esparza" userId="65b59e52a21d66fc" providerId="LiveId" clId="{01525AF4-9CFC-4414-9EAF-33FDE438DE6A}" dt="2026-04-08T10:20:56.691" v="20" actId="27636"/><ac:spMkLst><pc:docMk/><pc:sldMk cId="807981159" sldId="347"/><ac:spMk id="23" creationId="{00000000-0000-0000-0000-000000000000}"/></ac:spMkLst></pc:spChg><pc:spChg chg="del mod"><ac:chgData name="Alicia Esparza" userId="65b59e52a21d66fc" providerId="LiveId" clId="{01525AF4-9CFC-4414-9EAF-33FDE438DE6A}" dt="2026-04-12T23:08:55.034" v="825" actId="478"/><ac:spMkLst><pc:docMk/><pc:sldMk cId="807981159" sldId="347"/><ac:spMk id="25" creationId="{00000000-0000-0000-0000-000000000000}"/></ac:spMkLst></pc:spChg><pc:spChg chg="mod"><ac:chgData name="Alicia Esparza" userId="65b59e52a21d66fc" providerId="LiveId" clId="{01525AF4-9CFC-4414-9EAF-33FDE438DE6A}" dt="2026-04-08T10:20:56.689" v="18" actId="27636"/><ac:spMkLst><pc:docMk/><pc:sldMk cId="807981159" sldId="347"/><ac:spMk id="26" creationId="{00000000-0000-0000-0000-000000000000}"/></ac:spMkLst></pc:spChg><pc:graphicFrameChg chg="modGraphic"><ac:chgData name="Alicia Esparza" userId="65b59e52a21d66fc" providerId="LiveId" clId="{01525AF4-9CFC-4414-9EAF-33FDE438DE6A}" dt="2026-04-08T10:26:45.894" v="124" actId="403"/><ac:graphicFrameMkLst><pc:docMk/><pc:sldMk cId="807981159" sldId="347"/><ac:graphicFrameMk id="50" creationId="{00000000-0000-0000-0000-000000000000}"/></ac:graphicFrameMkLst></pc:graphicFrameChg></pc:sldChg><pc:sldChg chg="delSp modSp mod"><pc:chgData name="Alicia Esparza" userId="65b59e52a21d66fc" providerId="LiveId" clId="{01525AF4-9CFC-4414-9EAF-33FDE438DE6A}" dt="2026-04-12T23:09:10.083" v="826" actId="478"/><pc:sldMkLst><pc:docMk/><pc:sldMk cId="3601350240" sldId="348"/></pc:sldMkLst><pc:spChg chg="mod"><ac:chgData name="Alicia Esparza" userId="65b59e52a21d66fc" providerId="LiveId" clId="{01525AF4-9CFC-4414-9EAF-33FDE438DE6A}" dt="2026-04-08T10:20:56.719" v="30" actId="27636"/><ac:spMkLst><pc:docMk/><pc:sldMk cId="3601350240" sldId="348"/><ac:spMk id="20" creationId="{00000000-0000-0000-0000-000000000000}"/></ac:spMkLst></pc:spChg><pc:spChg chg="mod"><ac:chgData name="Alicia Esparza" userId="65b59e52a21d66fc" providerId="LiveId" clId="{01525AF4-9CFC-4414-9EAF-33FDE438DE6A}" dt="2026-04-12T23:07:01.819" v="811" actId="20577"/><ac:spMkLst><pc:docMk/><pc:sldMk cId="3601350240" sldId="348"/><ac:spMk id="21" creationId="{00000000-0000-0000-0000-000000000000}"/></ac:spMkLst></pc:spChg><pc:spChg chg="mod"><ac:chgData name="Alicia Esparza" userId="65b59e52a21d66fc" providerId="LiveId" clId="{01525AF4-9CFC-4414-9EAF-33FDE438DE6A}" dt="2026-04-12T23:07:32.019" v="819" actId="20577"/><ac:spMkLst><pc:docMk/><pc:sldMk cId="3601350240" sldId="348"/><ac:spMk id="22" creationId="{00000000-0000-0000-0000-000000000000}"/></ac:spMkLst></pc:spChg><pc:spChg chg="mod"><ac:chgData name="Alicia Esparza" userId="65b59e52a21d66fc" providerId="LiveId" clId="{01525AF4-9CFC-4414-9EAF-33FDE438DE6A}" dt="2026-04-12T23:07:19.365" v="815" actId="20577"/><ac:spMkLst><pc:docMk/><pc:sldMk cId="3601350240" sldId="348"/><ac:spMk id="23" creationId="{00000000-0000-0000-0000-000000000000}"/></ac:spMkLst></pc:spChg><pc:spChg chg="del mod"><ac:chgData name="Alicia Esparza" userId="65b59e52a21d66fc" providerId="LiveId" clId="{01525AF4-9CFC-4414-9EAF-33FDE438DE6A}" dt="2026-04-12T23:09:10.083" v="826" actId="478"/><ac:spMkLst><pc:docMk/><pc:sldMk cId="3601350240" sldId="348"/><ac:spMk id="25" creationId="{00000000-0000-0000-0000-000000000000}"/></ac:spMkLst></pc:spChg><pc:spChg chg="mod"><ac:chgData name="Alicia Esparza" userId="65b59e52a21d66fc" providerId="LiveId" clId="{01525AF4-9CFC-4414-9EAF-33FDE438DE6A}" dt="2026-04-08T10:20:56.721" v="33" actId="27636"/><ac:spMkLst><pc:docMk/><pc:sldMk cId="3601350240" sldId="348"/><ac:spMk id="26" creationId="{00000000-0000-0000-0000-000000000000}"/></ac:spMkLst></pc:spChg><pc:graphicFrameChg chg="modGraphic"><ac:chgData name="Alicia Esparza" userId="65b59e52a21d66fc" providerId="LiveId" clId="{01525AF4-9CFC-4414-9EAF-33FDE438DE6A}" dt="2026-04-08T10:28:21.456" v="146" actId="404"/><ac:graphicFrameMkLst><pc:docMk/><pc:sldMk cId="3601350240" sldId="348"/><ac:graphicFrameMk id="50" creationId="{00000000-0000-0000-0000-000000000000}"/></ac:graphicFrameMkLst></pc:graphicFrameChg></pc:sldChg><pc:sldChg chg="modSp mod ord"><pc:chgData name="Alicia Esparza" userId="65b59e52a21d66fc" providerId="LiveId" clId="{01525AF4-9CFC-4414-9EAF-33FDE438DE6A}" dt="2026-04-12T23:11:18.706" v="858" actId="20577"/><pc:sldMkLst><pc:docMk/><pc:sldMk cId="1777352268" sldId="349"/></pc:sldMkLst><pc:spChg chg="mod"><ac:chgData name="Alicia Esparza" userId="65b59e52a21d66fc" providerId="LiveId" clId="{01525AF4-9CFC-4414-9EAF-33FDE438DE6A}" dt="2026-04-08T10:20:56.745" v="41" actId="27636"/><ac:spMkLst><pc:docMk/><pc:sldMk cId="1777352268" sldId="349"/><ac:spMk id="20" creationId="{00000000-0000-0000-0000-000000000000}"/></ac:spMkLst></pc:spChg><pc:spChg chg="mod"><ac:chgData name="Alicia Esparza" userId="65b59e52a21d66fc" providerId="LiveId" clId="{01525AF4-9CFC-4414-9EAF-33FDE438DE6A}" dt="2026-04-12T23:10:53.372" v="850" actId="27636"/><ac:spMkLst><pc:docMk/><pc:sldMk cId="1777352268" sldId="349"/><ac:spMk id="21" creationId="{00000000-0000-0000-0000-000000000000}"/></ac:spMkLst></pc:spChg><pc:spChg chg="mod"><ac:chgData name="Alicia Esparza" userId="65b59e52a21d66fc" providerId="LiveId" clId="{01525AF4-9CFC-4414-9EAF-33FDE438DE6A}" dt="2026-04-12T23:11:06.864" v="854" actId="20577"/><ac:spMkLst><pc:docMk/><pc:sldMk cId="1777352268" sldId="349"/><ac:spMk id="22" creationId="{00000000-0000-0000-0000-000000000000}"/></ac:spMkLst></pc:spChg><pc:spChg chg="mod"><ac:chgData name="Alicia Esparza" userId="65b59e52a21d66fc" providerId="LiveId" clId="{01525AF4-9CFC-4414-9EAF-33FDE438DE6A}" dt="2026-04-12T23:11:18.706" v="858" actId="20577"/><ac:spMkLst><pc:docMk/><pc:sldMk cId="1777352268" sldId="349"/><ac:spMk id="23" creationId="{00000000-0000-0000-0000-000000000000}"/></ac:spMkLst></pc:spChg><pc:spChg chg="mod"><ac:chgData name="Alicia Esparza" userId="65b59e52a21d66fc" providerId="LiveId" clId="{01525AF4-9CFC-4414-9EAF-33FDE438DE6A}" dt="2026-04-08T10:20:56.758" v="44" actId="27636"/><ac:spMkLst><pc:docMk/><pc:sldMk cId="1777352268" sldId="349"/><ac:spMk id="26" creationId="{00000000-0000-0000-0000-000000000000}"/></ac:spMkLst></pc:spChg><pc:graphicFrameChg chg="modGraphic"><ac:chgData name="Alicia Esparza" userId="65b59e52a21d66fc" providerId="LiveId" clId="{01525AF4-9CFC-4414-9EAF-33FDE438DE6A}" dt="2026-04-08T10:28:41.558" v="153" actId="404"/><ac:graphicFrameMkLst><pc:docMk/><pc:sldMk cId="1777352268" sldId="349"/><ac:graphicFrameMk id="50" creationId="{00000000-0000-0000-0000-000000000000}"/></ac:graphicFrameMkLst></pc:graphicFrameChg></pc:sldChg><pc:sldChg chg="modSp mod"><pc:chgData name="Alicia Esparza" userId="65b59e52a21d66fc" providerId="LiveId" clId="{01525AF4-9CFC-4414-9EAF-33FDE438DE6A}" dt="2026-04-12T18:04:51.244" v="384" actId="20577"/><pc:sldMkLst><pc:docMk/><pc:sldMk cId="0" sldId="350"/></pc:sldMkLst><pc:spChg chg="mod"><ac:chgData name="Alicia Esparza" userId="65b59e52a21d66fc" providerId="LiveId" clId="{01525AF4-9CFC-4414-9EAF-33FDE438DE6A}" dt="2026-04-12T18:04:51.244" v="384" actId="20577"/><ac:spMkLst><pc:docMk/><pc:sldMk cId="0" sldId="350"/><ac:spMk id="4" creationId="{6D87D490-3233-91F6-7D20-9FABAD991375}"/></ac:spMkLst></pc:spChg><pc:picChg chg="mod"><ac:chgData name="Alicia Esparza" userId="65b59e52a21d66fc" providerId="LiveId" clId="{01525AF4-9CFC-4414-9EAF-33FDE438DE6A}" dt="2026-04-12T17:45:55.505" v="176" actId="14100"/><ac:picMkLst><pc:docMk/><pc:sldMk cId="0" sldId="350"/><ac:picMk id="2" creationId="{00000000-0000-0000-0000-000000000000}"/></ac:picMkLst></pc:picChg></pc:sldChg><pc:sldChg chg="addSp delSp modSp del mod"><pc:chgData name="Alicia Esparza" userId="65b59e52a21d66fc" providerId="LiveId" clId="{01525AF4-9CFC-4414-9EAF-33FDE438DE6A}" dt="2026-04-12T23:19:50.272" v="861" actId="22"/><pc:sldMkLst><pc:docMk/><pc:sldMk cId="2823852579" sldId="351"/></pc:sldMkLst><pc:spChg chg="mod"><ac:chgData name="Alicia Esparza" userId="65b59e52a21d66fc" providerId="LiveId" clId="{01525AF4-9CFC-4414-9EAF-33FDE438DE6A}" dt="2026-04-12T18:15:17.667" v="409" actId="14100"/><ac:spMkLst><pc:docMk/><pc:sldMk cId="2823852579" sldId="351"/><ac:spMk id="3" creationId="{00000000-0000-0000-0000-000000000000}"/></ac:spMkLst></pc:spChg><pc:spChg chg="mod"><ac:chgData name="Alicia Esparza" userId="65b59e52a21d66fc" providerId="LiveId" clId="{01525AF4-9CFC-4414-9EAF-33FDE438DE6A}" dt="2026-04-12T18:21:48.464" v="418" actId="20577"/><ac:spMkLst><pc:docMk/><pc:sldMk cId="2823852579" sldId="351"/><ac:spMk id="6" creationId="{00000000-0000-0000-0000-000000000000}"/></ac:spMkLst></pc:spChg><pc:picChg chg="mod"><ac:chgData name="Alicia Esparza" userId="65b59e52a21d66fc" providerId="LiveId" clId="{01525AF4-9CFC-4414-9EAF-33FDE438DE6A}" dt="2026-04-12T18:15:06.292" v="407" actId="14100"/><ac:picMkLst><pc:docMk/><pc:sldMk cId="2823852579" sldId="351"/><ac:picMk id="2" creationId="{00000000-0000-0000-0000-000000000000}"/></ac:picMkLst></pc:picChg><pc:picChg chg="add del"><ac:chgData name="Alicia Esparza" userId="65b59e52a21d66fc" providerId="LiveId" clId="{01525AF4-9CFC-4414-9EAF-33FDE438DE6A}" dt="2026-04-12T23:19:50.272" v="861" actId="22"/><ac:picMkLst><pc:docMk/><pc:sldMk cId="2823852579" sldId="351"/><ac:picMk id="8" creationId="{D34597CD-A3F8-405B-1221-D2370DC45CE0}"/></ac:picMkLst></pc:picChg></pc:sldChg><pc:sldChg chg="addSp delSp modSp mod"><pc:chgData name="Alicia Esparza" userId="65b59e52a21d66fc" providerId="LiveId" clId="{01525AF4-9CFC-4414-9EAF-33FDE438DE6A}" dt="2026-04-12T23:22:11.400" v="929" actId="14100"/><pc:sldMkLst><pc:docMk/><pc:sldMk cId="2007217994" sldId="352"/></pc:sldMkLst><pc:spChg chg="mod"><ac:chgData name="Alicia Esparza" userId="65b59e52a21d66fc" providerId="LiveId" clId="{01525AF4-9CFC-4414-9EAF-33FDE438DE6A}" dt="2026-04-12T23:21:40.619" v="926" actId="1076"/><ac:spMkLst><pc:docMk/><pc:sldMk cId="2007217994" sldId="352"/><ac:spMk id="3" creationId="{00000000-0000-0000-0000-000000000000}"/></ac:spMkLst></pc:spChg><pc:spChg chg="mod"><ac:chgData name="Alicia Esparza" userId="65b59e52a21d66fc" providerId="LiveId" clId="{01525AF4-9CFC-4414-9EAF-33FDE438DE6A}" dt="2026-04-12T23:20:14.192" v="877" actId="20577"/><ac:spMkLst><pc:docMk/><pc:sldMk cId="2007217994" sldId="352"/><ac:spMk id="4" creationId="{00000000-0000-0000-0000-000000000000}"/></ac:spMkLst></pc:spChg><pc:spChg chg="mod"><ac:chgData name="Alicia Esparza" userId="65b59e52a21d66fc" providerId="LiveId" clId="{01525AF4-9CFC-4414-9EAF-33FDE438DE6A}" dt="2026-04-12T23:21:36.067" v="925" actId="403"/><ac:spMkLst><pc:docMk/><pc:sldMk cId="2007217994" sldId="352"/><ac:spMk id="5" creationId="{00000000-0000-0000-0000-000000000000}"/></ac:spMkLst></pc:spChg><pc:spChg chg="del"><ac:chgData name="Alicia Esparza" userId="65b59e52a21d66fc" providerId="LiveId" clId="{01525AF4-9CFC-4414-9EAF-33FDE438DE6A}" dt="2026-04-12T23:20:30.820" v="882" actId="478"/><ac:spMkLst><pc:docMk/><pc:sldMk cId="2007217994" sldId="352"/><ac:spMk id="6" creationId="{00000000-0000-0000-0000-000000000000}"/></ac:spMkLst></pc:spChg><pc:spChg chg="del"><ac:chgData name="Alicia Esparza" userId="65b59e52a21d66fc" providerId="LiveId" clId="{01525AF4-9CFC-4414-9EAF-33FDE438DE6A}" dt="2026-04-12T23:20:17.826" v="878" actId="478"/><ac:spMkLst><pc:docMk/><pc:sldMk cId="2007217994" sldId="352"/><ac:spMk id="7" creationId="{00000000-0000-0000-0000-000000000000}"/></ac:spMkLst></pc:spChg><pc:spChg chg="del"><ac:chgData name="Alicia Esparza" userId="65b59e52a21d66fc" providerId="LiveId" clId="{01525AF4-9CFC-4414-9EAF-33FDE438DE6A}" dt="2026-04-12T23:20:27.602" v="881" actId="478"/><ac:spMkLst><pc:docMk/><pc:sldMk cId="2007217994" sldId="352"/><ac:spMk id="8" creationId="{00000000-0000-0000-0000-000000000000}"/></ac:spMkLst></pc:spChg><pc:picChg chg="add del mod"><ac:chgData name="Alicia Esparza" userId="65b59e52a21d66fc" providerId="LiveId" clId="{01525AF4-9CFC-4414-9EAF-33FDE438DE6A}" dt="2026-04-12T23:22:11.400" v="929" actId="14100"/><ac:picMkLst><pc:docMk/><pc:sldMk cId="2007217994" sldId="352"/><ac:picMk id="2" creationId="{00000000-0000-0000-0000-000000000000}"/></ac:picMkLst></pc:picChg></pc:sldChg><pc:sldChg chg="new del"><pc:chgData name="Alicia Esparza" userId="65b59e52a21d66fc" providerId="LiveId" clId="{01525AF4-9CFC-4414-9EAF-33FDE438DE6A}" dt="2026-04-12T23:00:44.262" v="761" actId="47"/><pc:sldMkLst><pc:docMk/><pc:sldMk cId="4257488231" sldId="352"/></pc:sldMkLst></pc:sldChg><pc:sldChg chg="delSp mod"><pc:chgData name="Alicia Esparza" userId="65b59e52a21d66fc" providerId="LiveId" clId="{01525AF4-9CFC-4414-9EAF-33FDE438DE6A}" dt="2026-04-12T23:57:25.273" v="930" actId="478"/><pc:sldMkLst><pc:docMk/><pc:sldMk cId="0" sldId="353"/></pc:sldMkLst><pc:spChg chg="del"><ac:chgData name="Alicia Esparza" userId="65b59e52a21d66fc" providerId="LiveId" clId="{01525AF4-9CFC-4414-9EAF-33FDE438DE6A}" dt="2026-04-12T23:57:25.273" v="930" actId="478"/><ac:spMkLst><pc:docMk/><pc:sldMk cId="0" sldId="353"/><ac:spMk id="85" creationId="{00000000-0000-0000-0000-000000000000}"/></ac:spMkLst></pc:spChg></pc:sldChg><pc:sldChg chg="delSp mod"><pc:chgData name="Alicia Esparza" userId="65b59e52a21d66fc" providerId="LiveId" clId="{01525AF4-9CFC-4414-9EAF-33FDE438DE6A}" dt="2026-04-12T23:58:14.768" v="932" actId="478"/><pc:sldMkLst><pc:docMk/><pc:sldMk cId="0" sldId="354"/></pc:sldMkLst><pc:spChg chg="del"><ac:chgData name="Alicia Esparza" userId="65b59e52a21d66fc" providerId="LiveId" clId="{01525AF4-9CFC-4414-9EAF-33FDE438DE6A}" dt="2026-04-12T23:58:14.768" v="932" actId="478"/><ac:spMkLst><pc:docMk/><pc:sldMk cId="0" sldId="354"/><ac:spMk id="78" creationId="{00000000-0000-0000-0000-000000000000}"/></ac:spMkLst></pc:spChg><pc:spChg chg="del"><ac:chgData name="Alicia Esparza" userId="65b59e52a21d66fc" providerId="LiveId" clId="{01525AF4-9CFC-4414-9EAF-33FDE438DE6A}" dt="2026-04-12T23:58:12.898" v="931" actId="478"/><ac:spMkLst><pc:docMk/><pc:sldMk cId="0" sldId="354"/><ac:spMk id="79" creationId="{00000000-0000-0000-0000-000000000000}"/></ac:spMkLst></pc:spChg></pc:sldChg><pc:sldChg chg="addSp modSp mod"><pc:chgData name="Alicia Esparza" userId="65b59e52a21d66fc" providerId="LiveId" clId="{01525AF4-9CFC-4414-9EAF-33FDE438DE6A}" dt="2026-04-13T01:32:17.346" v="958"/><pc:sldMkLst><pc:docMk/><pc:sldMk cId="0" sldId="356"/></pc:sldMkLst><pc:spChg chg="mod"><ac:chgData name="Alicia Esparza" userId="65b59e52a21d66fc" providerId="LiveId" clId="{01525AF4-9CFC-4414-9EAF-33FDE438DE6A}" dt="2026-04-13T01:26:21.515" v="949" actId="403"/><ac:spMkLst><pc:docMk/><pc:sldMk cId="0" sldId="356"/><ac:spMk id="200" creationId="{00000000-0000-0000-0000-000000000000}"/></ac:spMkLst></pc:spChg><pc:graphicFrameChg chg="modGraphic"><ac:chgData name="Alicia Esparza" userId="65b59e52a21d66fc" providerId="LiveId" clId="{01525AF4-9CFC-4414-9EAF-33FDE438DE6A}" dt="2026-04-13T01:26:40.959" v="950" actId="2164"/><ac:graphicFrameMkLst><pc:docMk/><pc:sldMk cId="0" sldId="356"/><ac:graphicFrameMk id="40" creationId="{00000000-0000-0000-0000-000000000000}"/></ac:graphicFrameMkLst></pc:graphicFrameChg><pc:graphicFrameChg chg="modGraphic"><ac:chgData name="Alicia Esparza" userId="65b59e52a21d66fc" providerId="LiveId" clId="{01525AF4-9CFC-4414-9EAF-33FDE438DE6A}" dt="2026-04-13T01:26:49.031" v="951" actId="2164"/><ac:graphicFrameMkLst><pc:docMk/><pc:sldMk cId="0" sldId="356"/><ac:graphicFrameMk id="50" creationId="{00000000-0000-0000-0000-000000000000}"/></ac:graphicFrameMkLst></pc:graphicFrameChg><pc:picChg chg="add mod"><ac:chgData name="Alicia Esparza" userId="65b59e52a21d66fc" providerId="LiveId" clId="{01525AF4-9CFC-4414-9EAF-33FDE438DE6A}" dt="2026-04-13T01:32:17.346" v="958"/><ac:picMkLst><pc:docMk/><pc:sldMk cId="0" sldId="356"/><ac:picMk id="4" creationId="{D0B1081E-995B-D737-5F11-A7C9E6932782}"/></ac:picMkLst></pc:picChg></pc:sldChg><pc:sldChg chg="modSp del mod"><pc:chgData name="Alicia Esparza" userId="65b59e52a21d66fc" providerId="LiveId" clId="{01525AF4-9CFC-4414-9EAF-33FDE438DE6A}" dt="2026-04-13T01:56:28.591" v="1033" actId="47"/><pc:sldMkLst><pc:docMk/><pc:sldMk cId="187558958" sldId="357"/></pc:sldMkLst><pc:spChg chg="mod"><ac:chgData name="Alicia Esparza" userId="65b59e52a21d66fc" providerId="LiveId" clId="{01525AF4-9CFC-4414-9EAF-33FDE438DE6A}" dt="2026-04-13T01:36:16.431" v="992" actId="1076"/><ac:spMkLst><pc:docMk/><pc:sldMk cId="187558958" sldId="357"/><ac:spMk id="23" creationId="{00000000-0000-0000-0000-000000000000}"/></ac:spMkLst></pc:spChg><pc:spChg chg="mod"><ac:chgData name="Alicia Esparza" userId="65b59e52a21d66fc" providerId="LiveId" clId="{01525AF4-9CFC-4414-9EAF-33FDE438DE6A}" dt="2026-04-13T01:36:57.449" v="1032" actId="403"/><ac:spMkLst><pc:docMk/><pc:sldMk cId="187558958" sldId="357"/><ac:spMk id="25" creationId="{00000000-0000-0000-0000-000000000000}"/></ac:spMkLst></pc:spChg><pc:picChg chg="mod"><ac:chgData name="Alicia Esparza" userId="65b59e52a21d66fc" providerId="LiveId" clId="{01525AF4-9CFC-4414-9EAF-33FDE438DE6A}" dt="2026-04-13T01:36:11.688" v="991" actId="1076"/><ac:picMkLst><pc:docMk/><pc:sldMk cId="187558958" sldId="357"/><ac:picMk id="3" creationId="{99F5ED79-44F4-E4D4-CA0C-0D3FE7DF5031}"/></ac:picMkLst></pc:picChg></pc:sldChg><pc:sldChg chg="delSp modSp mod"><pc:chgData name="Alicia Esparza" userId="65b59e52a21d66fc" providerId="LiveId" clId="{01525AF4-9CFC-4414-9EAF-33FDE438DE6A}" dt="2026-04-13T01:57:02.967" v="1036" actId="20577"/><pc:sldMkLst><pc:docMk/><pc:sldMk cId="566669161" sldId="358"/></pc:sldMkLst><pc:spChg chg="mod"><ac:chgData name="Alicia Esparza" userId="65b59e52a21d66fc" providerId="LiveId" clId="{01525AF4-9CFC-4414-9EAF-33FDE438DE6A}" dt="2026-04-13T01:57:02.967" v="1036" actId="20577"/><ac:spMkLst><pc:docMk/><pc:sldMk cId="566669161" sldId="358"/><ac:spMk id="12" creationId="{DF743168-AE1B-1BD3-1B0D-E94B43A6CCD5}"/></ac:spMkLst></pc:spChg><pc:picChg chg="del"><ac:chgData name="Alicia Esparza" userId="65b59e52a21d66fc" providerId="LiveId" clId="{01525AF4-9CFC-4414-9EAF-33FDE438DE6A}" dt="2026-04-13T01:56:32.700" v="1034" actId="478"/><ac:picMkLst><pc:docMk/><pc:sldMk cId="566669161" sldId="358"/><ac:picMk id="5" creationId="{1BD859D3-D4F9-EAC9-D434-307BEAE5A9DB}"/></ac:picMkLst></pc:picChg></pc:sldChg><pc:sldChg chg="modSp mod"><pc:chgData name="Alicia Esparza" userId="65b59e52a21d66fc" providerId="LiveId" clId="{01525AF4-9CFC-4414-9EAF-33FDE438DE6A}" dt="2026-04-13T02:10:27.484" v="1039" actId="123"/><pc:sldMkLst><pc:docMk/><pc:sldMk cId="790767001" sldId="359"/></pc:sldMkLst><pc:spChg chg="mod"><ac:chgData name="Alicia Esparza" userId="65b59e52a21d66fc" providerId="LiveId" clId="{01525AF4-9CFC-4414-9EAF-33FDE438DE6A}" dt="2026-04-13T02:10:27.484" v="1039" actId="123"/><ac:spMkLst><pc:docMk/><pc:sldMk cId="790767001" sldId="359"/><ac:spMk id="13" creationId="{442201AF-C917-1616-A0BC-878E3F47A53B}"/></ac:spMkLst></pc:spChg></pc:sldChg><pc:sldChg chg="new del"><pc:chgData name="Alicia Esparza" userId="65b59e52a21d66fc" providerId="LiveId" clId="{01525AF4-9CFC-4414-9EAF-33FDE438DE6A}" dt="2026-04-13T02:06:25.098" v="1038" actId="47"/><pc:sldMkLst><pc:docMk/><pc:sldMk cId="2668324855" sldId="360"/></pc:sldMkLst></pc:sldChg><pc:sldChg chg="delSp modSp mod"><pc:chgData name="Alicia Esparza" userId="65b59e52a21d66fc" providerId="LiveId" clId="{01525AF4-9CFC-4414-9EAF-33FDE438DE6A}" dt="2026-04-13T02:52:07.251" v="1129" actId="478"/><pc:sldMkLst><pc:docMk/><pc:sldMk cId="203382158" sldId="361"/></pc:sldMkLst><pc:spChg chg="mod"><ac:chgData name="Alicia Esparza" userId="65b59e52a21d66fc" providerId="LiveId" clId="{01525AF4-9CFC-4414-9EAF-33FDE438DE6A}" dt="2026-04-13T02:52:03.045" v="1128" actId="1076"/><ac:spMkLst><pc:docMk/><pc:sldMk cId="203382158" sldId="361"/><ac:spMk id="10" creationId="{F01D1F71-8566-3A82-6CC0-920418E90F4D}"/></ac:spMkLst></pc:spChg><pc:spChg chg="del"><ac:chgData name="Alicia Esparza" userId="65b59e52a21d66fc" providerId="LiveId" clId="{01525AF4-9CFC-4414-9EAF-33FDE438DE6A}" dt="2026-04-13T02:52:07.251" v="1129" actId="478"/><ac:spMkLst><pc:docMk/><pc:sldMk cId="203382158" sldId="361"/><ac:spMk id="12" creationId="{DF743168-AE1B-1BD3-1B0D-E94B43A6CCD5}"/></ac:spMkLst></pc:spChg><pc:picChg chg="mod"><ac:chgData name="Alicia Esparza" userId="65b59e52a21d66fc" providerId="LiveId" clId="{01525AF4-9CFC-4414-9EAF-33FDE438DE6A}" dt="2026-04-13T02:51:56.731" v="1127" actId="1076"/><ac:picMkLst><pc:docMk/><pc:sldMk cId="203382158" sldId="361"/><ac:picMk id="3" creationId="{99F5ED79-44F4-E4D4-CA0C-0D3FE7DF5031}"/></ac:picMkLst></pc:picChg></pc:sldChg><pc:sldChg chg="addSp modSp new mod"><pc:chgData name="Alicia Esparza" userId="65b59e52a21d66fc" providerId="LiveId" clId="{01525AF4-9CFC-4414-9EAF-33FDE438DE6A}" dt="2026-04-13T02:42:48.184" v="1078" actId="14100"/><pc:sldMkLst><pc:docMk/><pc:sldMk cId="34538131" sldId="362"/></pc:sldMkLst><pc:picChg chg="add mod"><ac:chgData name="Alicia Esparza" userId="65b59e52a21d66fc" providerId="LiveId" clId="{01525AF4-9CFC-4414-9EAF-33FDE438DE6A}" dt="2026-04-13T02:42:48.184" v="1078" actId="14100"/><ac:picMkLst><pc:docMk/><pc:sldMk cId="34538131" sldId="362"/><ac:picMk id="3" creationId="{03BC643E-F42C-F4C9-3151-95C4252C5565}"/></ac:picMkLst></pc:picChg></pc:sldChg><pc:sldChg chg="addSp modSp new mod"><pc:chgData name="Alicia Esparza" userId="65b59e52a21d66fc" providerId="LiveId" clId="{01525AF4-9CFC-4414-9EAF-33FDE438DE6A}" dt="2026-04-13T02:44:06.515" v="1085" actId="14100"/><pc:sldMkLst><pc:docMk/><pc:sldMk cId="1378377086" sldId="363"/></pc:sldMkLst><pc:picChg chg="add mod"><ac:chgData name="Alicia Esparza" userId="65b59e52a21d66fc" providerId="LiveId" clId="{01525AF4-9CFC-4414-9EAF-33FDE438DE6A}" dt="2026-04-13T02:44:06.515" v="1085" actId="14100"/><ac:picMkLst><pc:docMk/><pc:sldMk cId="1378377086" sldId="363"/><ac:picMk id="3" creationId="{5BFC6681-0262-C6BA-8EBD-DC0F93614AA8}"/></ac:picMkLst></pc:picChg></pc:sldChg><pc:sldChg chg="addSp modSp new mod"><pc:chgData name="Alicia Esparza" userId="65b59e52a21d66fc" providerId="LiveId" clId="{01525AF4-9CFC-4414-9EAF-33FDE438DE6A}" dt="2026-04-13T02:45:34.447" v="1091" actId="14100"/><pc:sldMkLst><pc:docMk/><pc:sldMk cId="3848496481" sldId="364"/></pc:sldMkLst><pc:picChg chg="add mod"><ac:chgData name="Alicia Esparza" userId="65b59e52a21d66fc" providerId="LiveId" clId="{01525AF4-9CFC-4414-9EAF-33FDE438DE6A}" dt="2026-04-13T02:45:34.447" v="1091" actId="14100"/><ac:picMkLst><pc:docMk/><pc:sldMk cId="3848496481" sldId="364"/><ac:picMk id="3" creationId="{2714F642-CD1F-5923-90FF-C70581710304}"/></ac:picMkLst></pc:picChg></pc:sldChg><pc:sldChg chg="addSp modSp new mod"><pc:chgData name="Alicia Esparza" userId="65b59e52a21d66fc" providerId="LiveId" clId="{01525AF4-9CFC-4414-9EAF-33FDE438DE6A}" dt="2026-04-13T02:46:40.018" v="1097" actId="14100"/><pc:sldMkLst><pc:docMk/><pc:sldMk cId="2745156808" sldId="365"/></pc:sldMkLst><pc:picChg chg="add mod"><ac:chgData name="Alicia Esparza" userId="65b59e52a21d66fc" providerId="LiveId" clId="{01525AF4-9CFC-4414-9EAF-33FDE438DE6A}" dt="2026-04-13T02:46:40.018" v="1097" actId="14100"/><ac:picMkLst><pc:docMk/><pc:sldMk cId="2745156808" sldId="365"/><ac:picMk id="3" creationId="{B09543D7-B035-BE3D-4913-3DE501EB833D}"/></ac:picMkLst></pc:picChg></pc:sldChg><pc:sldChg chg="addSp modSp new mod"><pc:chgData name="Alicia Esparza" userId="65b59e52a21d66fc" providerId="LiveId" clId="{01525AF4-9CFC-4414-9EAF-33FDE438DE6A}" dt="2026-04-13T02:49:54.256" v="1111" actId="14100"/><pc:sldMkLst><pc:docMk/><pc:sldMk cId="1861701660" sldId="366"/></pc:sldMkLst><pc:picChg chg="add mod modCrop"><ac:chgData name="Alicia Esparza" userId="65b59e52a21d66fc" providerId="LiveId" clId="{01525AF4-9CFC-4414-9EAF-33FDE438DE6A}" dt="2026-04-13T02:48:15.333" v="1104" actId="14100"/><ac:picMkLst><pc:docMk/><pc:sldMk cId="1861701660" sldId="366"/><ac:picMk id="3" creationId="{0FDAFE06-3AE6-E6BF-41C0-C35FF2746884}"/></ac:picMkLst></pc:picChg><pc:picChg chg="add mod"><ac:chgData name="Alicia Esparza" userId="65b59e52a21d66fc" providerId="LiveId" clId="{01525AF4-9CFC-4414-9EAF-33FDE438DE6A}" dt="2026-04-13T02:48:59.412" v="1107" actId="14100"/><ac:picMkLst><pc:docMk/><pc:sldMk cId="1861701660" sldId="366"/><ac:picMk id="5" creationId="{48C38607-7588-7D49-D57C-37AD29200DA9}"/></ac:picMkLst></pc:picChg><pc:picChg chg="add mod"><ac:chgData name="Alicia Esparza" userId="65b59e52a21d66fc" providerId="LiveId" clId="{01525AF4-9CFC-4414-9EAF-33FDE438DE6A}" dt="2026-04-13T02:49:54.256" v="1111" actId="14100"/><ac:picMkLst><pc:docMk/><pc:sldMk cId="1861701660" sldId="366"/><ac:picMk id="7" creationId="{89F8F4E6-4B7E-5F5C-D962-835C43496984}"/></ac:picMkLst></pc:picChg></pc:sldChg><pc:sldChg chg="addSp modSp new del mod"><pc:chgData name="Alicia Esparza" userId="65b59e52a21d66fc" providerId="LiveId" clId="{01525AF4-9CFC-4414-9EAF-33FDE438DE6A}" dt="2026-04-13T02:51:19.733" v="1115" actId="47"/><pc:sldMkLst><pc:docMk/><pc:sldMk cId="1761430384" sldId="367"/></pc:sldMkLst><pc:picChg chg="add mod"><ac:chgData name="Alicia Esparza" userId="65b59e52a21d66fc" providerId="LiveId" clId="{01525AF4-9CFC-4414-9EAF-33FDE438DE6A}" dt="2026-04-13T02:50:54.056" v="1114" actId="1076"/><ac:picMkLst><pc:docMk/><pc:sldMk cId="1761430384" sldId="367"/><ac:picMk id="3" creationId="{4B285F4C-FE6E-F996-9F0B-155439A2035C}"/></ac:picMkLst></pc:picChg></pc:sldChg></pc:docChg></pc:docChgLst></pc:chgInfo>